_epanet2.pyd
epanet2/epanet2.py
epanet2/epanettools.py
epanet2/__init__.py
epanet2/examples/simple/epanet2_test.py
epanet2/examples/simple/Net3.inp
EPANET2-0.4.0.1dev.dist-info/DESCRIPTION.rst
EPANET2-0.4.0.1dev.dist-info/METADATA
EPANET2-0.4.0.1dev.dist-info/metadata.json
EPANET2-0.4.0.1dev.dist-info/RECORD
EPANET2-0.4.0.1dev.dist-info/top_level.txt
EPANET2-0.4.0.1dev.dist-info/WHEEL
