Metadata-Version: 2.0
Name: EPANET2
Version: 0.4.0.1dev
Summary: EPANET 2.0  calls from python
Home-page: http://assela.pathirana.net/EPANET-Python
Author: Assela Pathirana
Author-email: assela@pathirana.net
License: GNU General Public License version 3
Platform: UNKNOWN
Classifier: Programming Language :: Python
Classifier: Programming Language :: Python :: 2.7
Classifier: Environment :: Other Environment
Classifier: Intended Audience :: Education
Classifier: Intended Audience :: Developers
Classifier: Intended Audience :: Science/Research
Classifier: License :: OSI Approved :: GNU General Public License v3 (GPLv3)
Classifier: Operating System :: POSIX
Classifier: Operating System :: Microsoft :: Windows
Classifier: Topic :: Software Development :: Libraries :: Python Modules
Classifier: Development Status :: 4 - Beta
Classifier: Natural Language :: English
